Metadata-Version: 2.4
Name: treepeat
Version: 0.4.0
Summary: treepeat: a tool to find similarities in a codebase
Author-email: Dane Summers <dsummersl@gmail.com>
License-Expression: Apache-2.0
Classifier: Programming Language :: Python :: 3
Classifier: Typing :: Typed
Requires-Python: >=3.11
Requires-Dist: click>=8.3.0
Requires-Dist: datasketch>=1.6.5
Requires-Dist: pydantic>=2.12.3
Requires-Dist: pydantic-settings>=2.0.0
Requires-Dist: python-magic>=0.4.27
Requires-Dist: rich>=14.2.0
Requires-Dist: sarif-pydantic>=0.6.2
Requires-Dist: tdqm>=0.0.1
Requires-Dist: tree-sitter>=0.25.2
Requires-Dist: tree-sitter-language-pack>=0.10.0
